sdml/kafka_client/__init__.py
sdml/kafka_client/types.py
sdml/kafka_client/clients/__init__.py
sdml/kafka_client/clients/base_client.py
sdml/kafka_client/clients/listener.py
sdml/kafka_client/clients/rpc.py
sdml_kafka_client-0.1.5.dist-info/METADATA
sdml_kafka_client-0.1.5.dist-info/WHEEL
sdml_kafka_client-0.1.5.dist-info/top_level.txt
sdml_kafka_client-0.1.5.dist-info/RECORD
