Metadata-Version: 2.4
Name: sdml-kafka-client
Version: 0.1.5
Summary: Kafka client for SDML
Requires-Python: >=3.12
Requires-Dist: aiokafka>=0.12.0
Requires-Dist: beartype>=0.22.2
Requires-Dist: loguru>=0.7.3
